arekit/__init__.py
arekit/common/__init__.py
arekit/common/bound.py
arekit/common/log_utils.py
arekit/common/utils.py
arekit/common/context/__init__.py
arekit/common/context/terms_mapper.py
arekit/common/context/token.py
arekit/common/data/__init__.py
arekit/common/data/const.py
arekit/common/data/doc_provider.py
arekit/common/data/rows_fmt.py
arekit/common/data/rows_parser.py
arekit/common/data/input/__init__.py
arekit/common/data/input/sample.py
arekit/common/data/input/terms_mapper.py
arekit/common/data/input/providers/__init__.py
arekit/common/data/input/providers/const.py
arekit/common/data/input/providers/contents.py
arekit/common/data/input/providers/columns/__init__.py
arekit/common/data/input/providers/columns/base.py
arekit/common/data/input/providers/columns/sample.py
arekit/common/data/input/providers/instances/__init__.py
arekit/common/data/input/providers/instances/base.py
arekit/common/data/input/providers/instances/multiple.py
arekit/common/data/input/providers/instances/single.py
arekit/common/data/input/providers/label/__init__.py
arekit/common/data/input/providers/label/base.py
arekit/common/data/input/providers/label/binary.py
arekit/common/data/input/providers/label/multiple.py
arekit/common/data/input/providers/rows/__init__.py
arekit/common/data/input/providers/rows/base.py
arekit/common/data/input/providers/rows/samples.py
arekit/common/data/input/providers/sample/__init__.py
arekit/common/data/input/providers/sample/cropped.py
arekit/common/data/input/providers/text/__init__.py
arekit/common/data/input/providers/text/single.py
arekit/common/data/storages/__init__.py
arekit/common/data/storages/base.py
arekit/common/docs/__init__.py
arekit/common/docs/base.py
arekit/common/docs/entities_grouping.py
arekit/common/docs/entity.py
arekit/common/docs/parser.py
arekit/common/docs/sentence.py
arekit/common/docs/parsed/__init__.py
arekit/common/docs/parsed/base.py
arekit/common/docs/parsed/service.py
arekit/common/docs/parsed/term_position.py
arekit-0.25.1.dist-info/LICENSE
arekit-0.25.1.dist-info/METADATA
arekit-0.25.1.dist-info/WHEEL
arekit-0.25.1.dist-info/top_level.txt
arekit-0.25.1.dist-info/RECORD
