Metadata-Version: 2.1
Name: arekit
Version: 0.25.1
Summary: Document level Attitude and Relation Extraction toolkit (AREkit) for sampling and prompting mass-media news into datasets for ML-model training
Home-page: https://github.com/nicolay-r/AREkit
Author: Nicolay Rusnachenko
Author-email: rusnicolay@gmail.com
License: MIT License
Keywords: natural language processing,relation extraction,sentiment analysis
Classifier: Programming Language :: Python
Classifier: Programming Language :: Python :: 3.6
Classifier: Topic :: Software Development :: Libraries :: Python Modules
Classifier: Topic :: Scientific/Engineering :: Information Analysis
Classifier: Topic :: Text Processing :: Linguistic
Requires-Python: >=3.6
License-File: LICENSE
Requires-Dist: tqdm
Requires-Dist: enum34==1.1.10
Requires-Dist: numpy>=1.14.5
